bigtest/__init__.py
bigtest/analytics.py
bigtest/backtest_config.py
bigtest/backtester.py
bigtest/backtester_v2.py
bigtest/data_engine.py
bigtest/day_trading_test_suite.py
bigtest/debug_alpaca.py
bigtest/deep_test_suite.py
bigtest/dukascopy_patch.py
bigtest/generate_report.py
bigtest/generated_strategy.py
bigtest/hf_scalper.py
bigtest/hf_scalper_v2.py
bigtest/main.py
bigtest/mean_rev_scalper.py
bigtest/ml_backtest_runner.py
bigtest/ml_hybrid_strategy.py
bigtest/ml_scalping_strategy.py
bigtest/ml_scalping_v2.py
bigtest/ml_trend_strategy.py
bigtest/pip_grabber.py
bigtest/profitable_scalper.py
bigtest/profitable_scalper_v2.py
bigtest/profitable_scalper_v3.py
bigtest/profitable_scalper_v4.py
bigtest/real_world_test_suite.py
bigtest/report_generator.py
bigtest/reporter.py
bigtest/run_1month_scalp.py
bigtest/scalp_test_suite.py
bigtest/simple_scalper.py
bigtest/strategy_engine.py
bigtest/strategy_test_suite.py
bigtest/stress_test_suite.py
bigtest/swing_test_suite.py
bigtest/test_backtest.py
bigtest/test_backtester_v2.py
bigtest/test_full_strategy.py
bigtest/trade_manager.py
bigtest/trade_simulator.py
bigtest/ultra_scalper.py
bigtest/utbot_backtest.py
bigtest-2.0.1.dist-info/METADATA
bigtest-2.0.1.dist-info/WHEEL
bigtest-2.0.1.dist-info/top_level.txt
bigtest-2.0.1.dist-info/RECORD
