Metadata-Version: 2.4
Name: bigtest
Version: 2.0.1
Summary: Holy Grail Backtester - Institutional-grade quant backtesting engine with 100x leverage support
Author: Kushal Garg
License: MIT
Project-URL: Homepage, https://github.com/kushalgarg/bigtest
Project-URL: Repository, https://github.com/kushalgarg/bigtest
Keywords: backtesting,trading,quantitative-finance,algorithmic-trading,forex,crypto,HFT
Classifier: Development Status :: 4 - Beta
Classifier: Intended Audience :: Financial and Insurance Industry
Classifier: License :: OSI Approved :: MIT License
Classifier: Operating System :: OS Independent
Classifier: Programming Language :: Python :: 3
Classifier: Programming Language :: Python :: 3.8
Classifier: Programming Language :: Python :: 3.9
Classifier: Programming Language :: Python :: 3.10
Classifier: Programming Language :: Python :: 3.11
Classifier: Programming Language :: Python :: 3.12
Classifier: Topic :: Office/Business :: Financial :: Investment
Requires-Python: >=3.8
Requires-Dist: pandas>=1.5.0
Requires-Dist: numpy>=1.21.0
Requires-Dist: plotly>=5.0.0
Requires-Dist: requests>=2.25.0
Requires-Dist: dukascopy-python>=0.1.0
Provides-Extra: alpaca
Requires-Dist: alpaca-trade-api>=3.0.0; extra == "alpaca"
Provides-Extra: binance
Requires-Dist: ccxt>=4.0.0; extra == "binance"
Provides-Extra: all
Requires-Dist: alpaca-trade-api>=3.0.0; extra == "all"
Requires-Dist: ccxt>=4.0.0; extra == "all"
